py3status_jenkins_status/__init__.py
py3status_jenkins_status/jenkins_status.py
py3status_jenkins_status/version.py
py3status_jenkins_status-0.0.4.dist-info/LICENSE
py3status_jenkins_status-0.0.4.dist-info/METADATA
py3status_jenkins_status-0.0.4.dist-info/WHEEL
py3status_jenkins_status-0.0.4.dist-info/entry_points.txt
py3status_jenkins_status-0.0.4.dist-info/top_level.txt
py3status_jenkins_status-0.0.4.dist-info/RECORD
