Metadata-Version: 2.1
Name: py3status-jenkins-status
Version: 0.0.4
Summary: py3status module to display the current jenkins job status
Home-page: https://gitlab.com/schmidtandreas/py3status-jenkins
Author: Andreas Schmidt
Author-email: mail@schmidt-andreas.de
License: UNKNOWN
Download-URL: https://gitlab.com/schmidtandreas/py3status-jenkins/tags
Project-URL: Documentation, https://py3status-jenkins.readthedocs.io/en/latest/
Platform: UNKNOWN
Classifier: Development Status :: 3 - Alpha
Classifier: Operating System :: POSIX :: Linux
Classifier: License :: OSI Approved :: MIT License
Classifier: Environment :: Console
Classifier: Topic :: Utilities
Classifier: Programming Language :: Python
Classifier: Programming Language :: Python :: 3.6
Classifier: Programming Language :: Python :: 3.7
Requires-Dist: py3status (>=3.20)
Requires-Dist: jenkins
Requires-Dist: pypass
Provides-Extra: lint
Requires-Dist: pre-commit ; extra == 'lint'
Provides-Extra: test
Requires-Dist: pytest ; extra == 'test'
Requires-Dist: py3status ; extra == 'test'
